alertmanager_mcp_server/__init__.py
alertmanager_mcp_server/server.py
alertmanager_mcp_server-1.1.0.dist-info/licenses/LICENSE
alertmanager_mcp_server-1.1.0.dist-info/METADATA
alertmanager_mcp_server-1.1.0.dist-info/WHEEL
alertmanager_mcp_server-1.1.0.dist-info/entry_points.txt
alertmanager_mcp_server-1.1.0.dist-info/top_level.txt
alertmanager_mcp_server-1.1.0.dist-info/RECORD
